{"cameraMode":{"drawMode":0,"name":"Shaded","section":"Shading Mode"},"sceneLighting":true,"audioPlay":false,"sceneViewState":{"m_AlwaysRefresh":false,"showFog":true,"showSkybox":true,"showFlares":true,"showImageEffects":true,"showParticleSystems":true,"showVisualEffectGraphs":true,"m_FxEnabled":true},"in2DMode":false,"pivot":{"x":39.27842712402344,"y":3.3437118530273439,"z":-85.21821594238281},"rotation":{"x":0.12296643108129502,"y":0.6823716163635254,"z":-0.11806277930736542,"w":0.7108044028282166},"size":76.52122497558594,"orthographic":false}